EV3PY/MediumMotor.py
EV3PY/__init__.py
EV3PY/myfunctions.py
EV3PY-0.1.1.dist-info/LICENCE.txt
EV3PY-0.1.1.dist-info/METADATA
EV3PY-0.1.1.dist-info/WHEEL
EV3PY-0.1.1.dist-info/top_level.txt
EV3PY-0.1.1.dist-info/RECORD
