Metadata-Version: 2.1
Name: EV3PY
Version: 0.1.1
Summary: Convert Python Code to EV3 Code
Home-page: UNKNOWN
Author: Fynn Krebser
Author-email: fynn.krebser@gmail.com
License: MIT
Keywords: EV3
Platform: UNKNOWN
License-File: LICENCE.txt
